Albion_GLS/Albion_int.py
Albion_GLS/Charts.py
Albion_GLS/Edisan.py
Albion_GLS/Sewsan.py
Albion_GLS/TSNET_Interface.py
Albion_GLS/WNTR_Interface.py
Albion_GLS/Wadiso.py
Albion_GLS/__init__.py
albion_gls-0.2.5.dist-info/METADATA
albion_gls-0.2.5.dist-info/WHEEL
albion_gls-0.2.5.dist-info/top_level.txt
albion_gls-0.2.5.dist-info/RECORD
