Metadata-Version: 2.4
Name: Albion_GLS
Version: 0.2.5
Summary: Albion Interface
Author-email: GLS <software@gls.co.za>
License: Proprietary
Keywords: python,first package
Classifier: Development Status :: 3 - Alpha
Classifier: Intended Audience :: Science/Research
Classifier: Programming Language :: Python :: 3
Classifier: Operating System :: Microsoft :: Windows
Requires-Python: >=3.7
